alu_defines.vh
`ifndef ALU_DEFINES
`define ALU_DEFINES

`define OPER_BITS	2
`define ALU_SUB		`OPER_BITS'b00
`define ALU_LESS	`OPER_BITS'b01
`define ALU_INDB	`OPER_BITS'b10
`define ALU_CHANGE	`OPER_BITS'b11

`endif

ALU.sv
`include "alu_defines.vh"

module ALU (i_op, i_arg_A, i_arg_B, i_clk, i_reset, o_result, o_status);

	parameter N = 2;
	parameter M = 8;
	
    	input logic [N-1:0] i_op;
    	input logic [M-1:0] i_arg_A;
    	input logic [M-1:0] i_arg_B;
    	input logic i_clk;
    	input logic i_reset;
    	output logic [M-1:0] o_result;
    	output logic [3:0] o_status;
	

    	always @(posedge i_clk) begin
    	
    		o_status = 4'b0000; 
    		
    		case (i_op)
    			
    			
    			`ALU_SUB : // A-2*B
    				
    					o_result = i_arg_A - (2 * i_arg_B);
    				
                    	//`ALU_LESS   : // A < B
				
				//if (i_arg_A < i_arg_B) begin
    				//	o_status[0] = 1;
    				//end
    				//if ((i_arg_A + i_arg_B)[$unsigned(i_arg_B)] == 0) begin
                    		//	o_status[1] = 1;
                    		//end
				                    	
                    	//`ALU_INDB   : // (A+B)[B] = 0	
                    			
                    	//`ALU_CHANGE : // U2(A) => ZM(A)
			                    			
                    	//default:
		endcase
    	end
endmodule

testbench.sv
`timescale 1ps/1ps
`include "./ALU.sv"


module testbench_ALU;

    parameter s_N = 2;
    parameter s_M = 8;


    reg [s_N-1:0] s_op;
    reg [s_M-1:0] s_arg_A;
    reg [s_M-1:0] s_arg_B;
    reg s_clk;
    reg s_reset;

    wire [s_M-1:0] sim_result;
    wire [3:0] sim_status;

    wire [s_M-1:0] syn_result;
    wire [3:0] syn_status;


    ALU #(.N(s_N), .M(s_M)) 
    	alu_model_simulation (
    		.i_arg_A(s_arg_A), 
 		.i_arg_B(s_arg_B), 
 		.i_op(s_op), 
 		.i_clk(s_clk), 
 		.i_reset(s_reset), 
 		.o_result(sim_result), 
 		.o_status(sim_status)
 	);	
 	
    ALU
    	alu_model_synthesis (
    		.i_arg_A(s_arg_A), 
    		.i_arg_B(s_arg_B), 
    		.i_op(s_op), 
    		.i_clk(s_clk), 
    		.i_reset(s_reset), 
    		.o_result(syn_result), 
    		.o_status(syn_status));    

    initial begin
        $dumpfile("signals.vcd");
        $dumpvars(0, testbench_ALU);

        s_reset = 1'b1;
    	s_op = 2'b00;
        
        /*Y = 2 + 3 */
        s_clk = 0;
        s_arg_A = 8'b00000010;
        s_arg_B = 8'b11111100;
        #1
        s_clk = 1;
        #1
        
        /*Y = 126 + 1 */
        s_clk = 0;
        s_arg_A = 8'b01111110;
        s_arg_B = 8'b11111110;
        #1
        s_clk = 1;
        #1
        
        /*Y = 126 + 2 */
        s_clk = 0;
        s_arg_A = 8'b01111110;
        s_arg_B = 8'b11111100;
        #1
        s_clk = 1;
        #1
        
        /*Y = -126 + 3 */
        s_clk = 0;
        s_arg_A = 8'b11111110;
        s_arg_B = 8'b11111100;
        #1
        s_clk = 1;
        #1
        
        $finish;
    end
endmodule

signals.vcd
$date
	Sun Nov 26 00:51:02 2023
$end
$version
	Icarus Verilog
$end
$timescale
	1ps
$end
$scope module testbench_ALU $end
$var wire 4 ! syn_status [3:0] $end
$var wire 8 " syn_result [7:0] $end
$var wire 4 # sim_status [3:0] $end
$var wire 8 $ sim_result [7:0] $end
$var reg 8 % s_arg_A [7:0] $end
$var reg 8 & s_arg_B [7:0] $end
$var reg 1 ' s_clk $end
$var reg 2 ( s_op [1:0] $end
$var reg 1 ) s_reset $end
$scope module alu_model_simulation $end
$var wire 8 * i_arg_A [7:0] $end
$var wire 8 + i_arg_B [7:0] $end
$var wire 1 ' i_clk $end
$var wire 2 , i_op [1:0] $end
$var wire 1 ) i_reset $end
$var reg 8 - o_result [7:0] $end
$var reg 4 . o_status [3:0] $end
$upscope $end
$scope module alu_model_synthesis $end
$var wire 8 / i_arg_A [7:0] $end
$var wire 8 0 i_arg_B [7:0] $end
$var wire 1 ' i_clk $end
$var wire 2 1 i_op [1:0] $end
$var wire 1 ) i_reset $end
$var reg 8 2 o_result [7:0] $end
$var reg 4 3 o_status [3:0] $end
$upscope $end
$upscope $end
$enddefinitions $end
#0
$dumpvars
bx 3
bx 2
b0 1
b11111100 0
b10 /
bx .
bx -
b0 ,
b11111100 +
b10 *
1)
b0 (
0'
b11111100 &
b10 %
bx $
bx #
bx "
bx !
$end
#1
b1010 $
b1010 -
b0 #
b0 .
b1010 "
b1010 2
b0 !
b0 3
1'
#2
b11111110 &
b11111110 +
b11111110 0
b1111110 %
b1111110 *
b1111110 /
0'
#3
b10000010 "
b10000010 2
b10000010 $
b10000010 -
1'
#4
b11111100 &
b11111100 +
b11111100 0
0'
#5
b10000110 $
b10000110 -
b10000110 "
b10000110 2
1'
#6
b11111110 %
b11111110 *
b11111110 /
0'
#7
b110 "
b110 2
b110 $
b110 -
1'
