ALU/alu.sv
`define ALU_SUB 2'b00
`define ALU_COMP 2'b01
`define ALU_SUM 2'b10
`define ALU_CONV 2'b11

module sync_arith_unit_4 (i_op, 
						i_arg_A, 
						i_arg_B, 
						i_clk, 
						i_reset, 
						o_result, 
						o_status);

	/* parameters used to keep the code easy to modify */
	parameter N = 2, M = 4, J = 5;

	/* logical inputs, specified in documentation */
	input logic [N-1:0] i_op;
	input logic [M-1:0] i_arg_A, i_arg_B;
	input logic i_clk;
	input logic i_reset;

	/* logical outputs, specified in documentation */
	output logic [M-1:0] o_result;
	output logic [3:0] o_status;
	
	/* logical vectors, to keep temporary values inside of them
	   this way, im not modyfing the output over and over again, 
	   but instead perform operation on temporary vars
	*/
	logic [M-1:0] temp_B;
	logic [M-1:0] comp_A, comp_B;
	logic [M-1:0] sum;
	logic [J-1:0] overflow_check;
	
	/* temporary result and status to keep a track of em in combination part of module */
	logic [3:0] temp_status; 
	logic [M-1:0] temp_result;
	
	logic signed [M-1:0] s_A, s_B;
	
	/* Combination part of the module */
	always_comb begin
    	
    		/* Zeroing the status output */
    		
    		
    		/* assigning zero-values to temporary result and status*/
    		temp_status = 4'b0000; 
    		temp_result = 4'b0;
    		
    		/* assigning zero-values to temporary vars*/
    		temp_B = 4'b0;
    		comp_A = 4'b0; comp_B = 4'b0;
    		sum = 4'b0;
    		overflow_check = 5'b0;
    		
    		/* starting the switch case for all operation options */
    		
    		case (i_op)
    		
    		
    			/*------------FIRST OPERATION------------*/
    			
    			/* Operation of subtracting the double of B from A */
    			
    			`ALU_SUB:  begin // A-2*B
    					/*	
    					temp_B = (i_arg_B << 1);
    					
    					s_B = $signed(temp_B);
    					s_A = $signed(i_arg_A);
    					
    					if ((s_A - s_B) > ((2**(M-1)) - 1)) 
    					begin
        					temp_status = 4'b1001;
    						temp_result = 4'bx;
        				end 
        				else if ((s_A - s_B) < ((2**(M-1)) - 1)) 
        				begin
        					temp_status = 4'b1001;
    						temp_result = 4'bx;
        				end else 
        				begin
        					temp_result = s_A - s_B;
        				end
    					*/
    					/* addressing the problem with overflow and goind out of bounds */
    					/*
    					overflow_check = i_arg_A - temp_B;
    					
    					if ((overflow_check[J-1] == 0) && (overflow_check[J-2] == 1)) 
    					begin
    					
    						temp_status = 4'b1001;
    						temp_result = 4'bx;
    						
    					end 
    					else if ((overflow_check[J-1] == 1) && (overflow_check[J-2] == 0))  
    					begin
    					
    						temp_status = 4'b1001;
    						temp_result = 4'bx;
    						
    					end else 
    					begin 
    					
    						temp_result = i_arg_A - temp_B;
    					
    					end
    					*/
    					temp_B = (i_arg_B << 1);
    					
            			s_A = $signed(i_arg_A);
        			 	s_B = $signed(temp_B);
        				
  
        				if ((s_A - s_B) > ((2**(M-1)) - 1)) begin
        					temp_status = 4'b1001;
    						temp_result = 4'bx;
        				end 
        				else if ((s_A - s_B) < -(2**(M-1))) begin
        					temp_status = 4'b1001;
    						temp_result = 4'bx;
        				end else begin
        				
        				sum = s_A - s_B;
        				temp_result = sum;

        				end
        				
                    end
      
            		
            			
            	/*------------SECOND OPERATION------------*/
            			
            	/* Operation of comparing input A with input B */
            	
            	`ALU_COMP: begin // A < B
                    	 
                    	/* if A is smaller than B then the output is NOT 0 */ 
                    	
                		if ((i_arg_A[M-1] == 1) && (i_arg_B[M-1] == 0)) 
                		begin
                		
                    			temp_result = 2'b01; 
                    			
                		end else 
                		
                		/* if A is bigger than B then the output is 0 */ 
                		
                		if (((i_arg_A[M-1] == 0) && (i_arg_B[M-1] == 1)) || (i_arg_A == i_arg_B)) 
                		begin
                		
                    			temp_result = 0; // Output 0 if A >= B
                    			
                		end else if ((i_arg_A[M-1] == 0) && (i_arg_B[M-1] == 0)) 
                		begin
                		
                			if (i_arg_A < i_arg_B) 
                			begin
                			
                				temp_result = 2'b01; 
                				
                			end else 
                			begin 
                			
                				temp_result = 0;
                				
                			end
                			
                		end else if ((i_arg_A[M-1] == 1) && (i_arg_B[M-1] == 1)) 
                		begin
                			comp_A = i_arg_A;
                			comp_B = i_arg_B;
                			
                			comp_A[M-1] = 0;
                			comp_B[M-1] = 0;
                			
                			if (comp_A > comp_B) 
                			begin
                			
                				temp_result = 1;
                			
                			end else 
                			begin
                			
                				temp_result = 0;
                			
                			end
                		
                		end

            		end 
            	
            	
            	
            	/*------------THIRD OPERATION------------*/ 
            	
            	/* Operation of changing the B-index bit of the sum ofg  */
   
        		`ALU_SUM : begin // (A+B)[B] = 0

        			 	/* Adding up both input vectors, A and B */
        			 	
        			 	s_A = $signed(i_arg_A);
        			 	s_B = $signed(i_arg_B);
        			 	
        				//sum = i_arg_A + i_arg_B;
        				//overflow_check = sum;
        				
        				
        				
        				/*
        				if ((overflow_check[J-1] == 0) && ((overflow_check[J-2] == 1)))
    					begin
    					
    						temp_status = 4'b1001;
    						temp_result = 4'bx;
    						
    						
    					end else if ((overflow_check[J-1] == 1) && ((overflow_check[J-2] == 0)))
    					begin
    					
    						temp_status = 4'b1001;
    						temp_result = 4'bx;
    						
    					end else
        				begin
        				*/
        				/*  
        					Changing the corresponded to B value bit in sum to 0 
        					keep in mind the bits are 0 indexed, so if B = 0001 then 
        					in "sum" the bit changed will be the 2^1 one.
        				*/ 
        				if ((s_A + s_B) > ((2**(M-1)) - 1)) begin
        					temp_status = 4'b1001;
    						temp_result = 4'bx;
        				end 
        				else if ((s_A + s_B) < -(2**(M-1))) begin
        					temp_status = 4'b1001;
    						temp_result = 4'bx;
        				end else begin
        				
        				sum = s_A + s_B;
        				sum = (sum & ~(1 << s_B));

        				
        				/* Assigning the sum to the result output */
        				
        				temp_result = sum;
        				end
        				
                    end
                    	
                    	
                    	
                    	
               	/*------------FOURTH OPERATION------------*/		
               		
                /*  Fourth operation, conversion from Two's compliment into sign magnitude (U2 into ZM)*/
                    			
                    			
               	`ALU_CONV: begin // U2(A) => ZM(A)
    				
    					/* if the number is negative, we invert all but first bits, then add 1 */
    				
    					if(i_arg_A[M-1] == 1) 
    					begin
    				
        					temp_result = {1'b1, ~(i_arg_A[M-2:0]) + 1'b1};
        				
    					end 
    				
    					/* if the number is positive, then the output is the number itself*/
    				
    					else begin
    				
        					temp_result = i_arg_A;
        				
    					end
    					
					end
    			
    			
                    //default - not used
                    
			endcase
				
			/* After exiting switch case, assigning bits of the temp_status */
				
				if (~(temp_status == 4'b1001))
				begin 
					
				/* If there is an even number of ones in result, switch bit no.2 to 1 */
					
					if(~(^temp_result == 1'b1)) 
					begin
						temp_status[2] = 1'b1;
					end
				
				/* If result is made of ones entirely, switch bit no.1 to 1 */
				
					if(temp_result == 4'b1111) 
					begin
						temp_status[1] = 1'b1; 
					end
					
				end	
				
			/* reseting the entire module */
				if(i_reset == 1'b0) 
				begin
				    temp_status = 4'b0000;
    				temp_result = 4'b0000;
				end

    	end
		
		/* assigning the temporary result and status to their outputs */
    	always_ff @(posedge i_clk) begin
    		o_result <= temp_result;
    		o_status <= temp_status;
   		end

endmodule

ALU/testbench.sv
`timescale 1ps/1ps
`include "./alu.sv"


module testbench;

    parameter test_N = 2;
    parameter test_M = 4;

    
    reg [test_N-1:0] test_op;
    reg [test_M-1:0] test_arg_A;
    reg [test_M-1:0] test_arg_B;
    reg test_clk;
    reg test_reset;
    
    wire [test_M-1:0] simulation_test_result;
    wire [3:0] simulation_test_status;

    //wire [test_M-1:0] synthesis_test_result;
    //wire [3:0] synthesis_test_status;
    
    sync_arith_unit_4 #(.N(test_N), .M(test_M))
    alu_model_simulation
    					(.i_arg_A(test_arg_A),
    					 .i_arg_B(test_arg_B),
    					 .i_op(test_op),
    					 .i_clk(test_clk),
    				     .i_reset(test_reset),
    				     .o_result(simulation_test_result), 
    			   	     .o_status(simulation_test_status));
	
	initial begin
		
		$dumpfile("signals.vcd");
		$dumpvars(0, testbench);
		
		
		
	/*---------FIRST OPERATION TEST---------*/

	test_op = 2'b00;
	test_reset = 1'b1;

		// Test Case 1: A = 3, B = 2
		test_clk = 0; test_arg_A = 4'b0011; test_arg_B = 4'b0010;	
		#1 test_clk = 1; #1
		/* expected output: 1111 */
		/* expected status: 0110 */

		// Test Case 2: A = -1, B = 3
		test_clk = 0; test_arg_A = 4'b1111; test_arg_B = 4'b0011;
		#1 test_clk = 1; #1
        /* expected output: 1001 */
		/* expected status: 0100 */

		// Test Case 6: A = -3, B = 3
		test_clk = 0; test_arg_A = 4'b1101; test_arg_B = 4'b0011;
		#1 test_clk = 1; #1
        /* expected output: WHATEVER (xxxx) */
		/* expected status: 1001 */

		// Test Case 3: A = -2, B = -4
		test_clk = 0; test_arg_A = 4'b1110; test_arg_B = 4'b1100;
		#1 test_clk = 1; #1
        /* expected output: 0110 */
		/* expected status: 0000 */

		// Test Case 4: A = 1, B = 3
		test_clk = 0; test_arg_A = 4'b0001; test_arg_B = 4'b0011;
		#1 test_clk = 1; #1
        /* expected output: 1011 */
		/* expected status: 0100 */

		// Test Case 5: A = 4, B = 2
		test_clk = 0; test_arg_A = 4'b0100; test_arg_B = 4'b0010;
		#1 test_clk = 1; #1
        /* expected output: 0000 */
		/* expected status: 0100 */

		// Test Case 7: A = 5, B = -3
		test_clk = 0; test_arg_A = 4'b0101; test_arg_B = 4'b1101;
		#1 test_clk = 1; #1
        /* expected output: WHATEVER (xxxx) */
		/* expected status: 1001 */

		// Test Case 8: A = 4, B = 5
		test_clk = 0; test_arg_A = 4'b0100; test_arg_B = 4'b0101;
		#1 test_clk = 1; #1
        /* expected output: WHATEVER */
		/* expected status: 1001 */



	/*---------SECOND OPERATION TEST---------*/

	test_op = 2'b01;

		// Test Case 1: A = 3, B = 5
		test_clk = 0; test_arg_A = 4'b0011; test_arg_B = 4'b0101;
		#1 test_clk = 1; #1
		// Expected output: 1
		// Expected status: 0000

		// Test Case 2: A = 7, B = 4
		test_clk = 0; test_arg_A = 4'b0111; test_arg_B = 4'b0100;
		#1 test_clk = 1; #1
		// Expected output: 0
		// Expected status: 0100

		// Test Case 3: A = -4, B = 3
		test_clk = 0; test_arg_A = 4'b1100; test_arg_B = 4'b0011;
		#1 test_clk = 1; #1
		// Expected output: 1
		// Expected status: 0000

		// Test Case 4: A = -3, B = -3
		test_clk = 0; test_arg_A = 4'b1101; test_arg_B = 4'b1101;
		#1 test_clk = 1; #1
		// Expected output: 0
		// Expected status: 0100

		// Test Case 5: A = 4, B = -5
		test_clk = 0; test_arg_A = 4'b0100; test_arg_B = 4'b1011;
		#1 test_clk = 1; #1
		// Expected output: 0
		// Expected status: 0100

		// Test Case 6: A = 0, B = 5
		test_clk = 0; test_arg_A = 4'b0000; test_arg_B = 4'b0101;
		#1 test_clk = 1; #1
		// Expected output: 1
		// Expected status: 0000



	/*---------THIRD OPERATION TEST---------*/

	test_op = 2'b10;

		// Test Case 1: A = 2, B = 3
		test_clk = 0; test_arg_A = 4'b0010; test_arg_B = 4'b0011;
		#1 test_clk = 1; #1
        /* expected output: 0101 */
		/* expected status: 0100 */

		// Test Case 2: A = 2, B = 1
		test_clk = 0; test_arg_A = 4'b0010; test_arg_B = 4'b0001;
		#1 test_clk = 1; #1
        /* expected output: 0001 */
		/* expected status: 0000 */

		// Test Case 3: A = -3, B = 1
		test_clk = 0; test_arg_A = 4'b1101; test_arg_B = 4'b0001;
		#1 test_clk = 1; #1
        /* expected output: 1100 */
		/* expected status: 0000 */

		// Test Case 4: A = 6, B = 3
		test_clk = 0; test_arg_A = 4'b0110; test_arg_B = 4'b0011;
		#1 test_clk = 1; #1
        /* expected output: WHATEVER */
		/* expected status: 1001 */

		// Test Case 5: A = 7, B = 0
		test_clk = 0; test_arg_A = 4'b0111; test_arg_B = 4'b0000;
		#1 test_clk = 1; #1
        /* expected output: 0110 */
		/* expected status: 0100 */



	/*---------FOURTH OPERATION TEST---------*/

	test_op = 2'b11;

		// Test Case 1: A = 3
		test_clk = 0; test_arg_A = 4'b0011;
		#1 test_clk = 1; #1
		// Expected output: 0011
		// Expected status: 0100

		// Test Case 2: A = 7
		test_clk = 0; test_arg_A = 4'b0111;
		#1 test_clk = 1; #1
		// Expected output: 0111
		// Expected status: 0000

		// Test Case 3: A = 0
		test_clk = 0; test_arg_A = 4'b0000;
        #1 test_clk = 1; #1
        /* expected output: 0000 */
		/* expected status: 0100 */
		
		// Test Case 3: A = -5
		test_clk = 0; test_arg_A = 4'b1011;
        #1 test_clk = 1; #1
        /* expected output: 1101 */
		/* expected status: 0000 */

		// Test Case 3: A = -7
		test_clk = 0; test_arg_A = 4'b1001;
        #1 test_clk = 1; #1
        /* expected output: 1111 */
		/* expected status: 0S0 */
		
		$finish;
	
	end
		
endmodule

ALU/signals.vcd
$date
	Sun Dec 10 13:03:04 2023
$end
$version
	Icarus Verilog
$end
$timescale
	1ps
$end
$scope module testbench $end
$var wire 4 ! simulation_test_status [3:0] $end
$var wire 4 " simulation_test_result [3:0] $end
$var reg 4 # test_arg_A [3:0] $end
$var reg 4 $ test_arg_B [3:0] $end
$var reg 1 % test_clk $end
$var reg 2 & test_op [1:0] $end
$var reg 1 ' test_reset $end
$scope module alu_model_simulation $end
$var wire 4 ( i_arg_A [3:0] $end
$var wire 4 ) i_arg_B [3:0] $end
$var wire 1 % i_clk $end
$var wire 2 * i_op [1:0] $end
$var wire 1 ' i_reset $end
$var reg 4 + comp_A [3:0] $end
$var reg 4 , comp_B [3:0] $end
$var reg 4 - o_result [3:0] $end
$var reg 4 . o_status [3:0] $end
$var reg 5 / overflow_check [4:0] $end
$var reg 4 0 s_A [3:0] $end
$var reg 4 1 s_B [3:0] $end
$var reg 4 2 sum [3:0] $end
$var reg 4 3 temp_B [3:0] $end
$var reg 4 4 temp_result [3:0] $end
$var reg 4 5 temp_status [3:0] $end
$upscope $end
$upscope $end
$enddefinitions $end
#0
$dumpvars
b110 5
b1111 4
b100 3
b1111 2
b100 1
b11 0
b0 /
bx .
bx -
b0 ,
b0 +
b0 *
b10 )
b11 (
1'
b0 &
0%
b10 $
b11 #
bx "
bx !
$end
#1
b110 !
b110 .
b1111 "
b1111 -
1%
#2
b110 1
b1111 0
b1001 2
b110 3
b1001 4
b100 5
b11 $
b11 )
b1111 #
b1111 (
0%
#3
b100 !
b100 .
b1001 "
b1001 -
1%
#4
b1101 0
b0 2
b110 3
bx 4
b1001 5
b1101 #
b1101 (
0%
#5
b1001 !
b1001 .
bx "
bx -
1%
#6
b110 2
b1000 1
b1110 0
b1000 3
b110 4
b100 5
b1100 $
b1100 )
b1110 #
b1110 (
0%
#7
b100 !
b100 .
b110 "
b110 -
1%
#8
b110 1
b1 0
b1011 2
b110 3
b1011 4
b0 5
b11 $
b11 )
b1 #
b1 (
0%
#9
b0 !
b0 .
b1011 "
b1011 -
1%
#10
b100 5
b100 1
b100 0
b0 2
b100 3
b0 4
b10 $
b10 )
b100 #
b100 (
0%
#11
b100 !
b100 .
b0 "
b0 -
1%
#12
bx 4
b1010 1
b101 0
b1010 3
b1001 5
b1101 $
b1101 )
b101 #
b101 (
0%
#13
b1001 !
b1001 .
bx "
bx -
1%
#14
b100 0
b1010 3
bx 4
b1001 5
b101 $
b101 )
b100 #
b100 (
0%
#15
1%
#16
b0 3
b1 4
b0 5
b11 #
b11 (
0%
b1 &
b1 *
#17
b0 !
b0 .
b1 "
b1 -
1%
#18
b100 5
b0 4
b100 $
b100 )
b111 #
b111 (
0%
#19
b100 !
b100 .
b0 "
b0 -
1%
#20
b1 4
b0 5
b11 $
b11 )
b1100 #
b1100 (
0%
#21
b0 !
b0 .
b1 "
b1 -
1%
#22
b100 5
b0 4
b1101 $
b1101 )
b1101 #
b1101 (
0%
#23
b100 !
b100 .
b0 "
b0 -
1%
#24
b100 5
b1011 $
b1011 )
b100 #
b100 (
0%
#25
1%
#26
b1 4
b0 5
b101 $
b101 )
b0 #
b0 (
0%
#27
b0 !
b0 .
b1 "
b1 -
1%
#28
b100 5
b101 2
b11 1
b10 0
b101 4
b11 $
b11 )
b10 #
b10 (
0%
b10 &
b10 *
#29
b100 !
b100 .
b101 "
b101 -
1%
#30
b1 1
b1 2
b1 4
b0 5
b1 $
b1 )
0%
#31
b0 !
b0 .
b1 "
b1 -
1%
#32
b100 5
b1101 0
b1100 2
b1100 4
b1101 #
b1101 (
0%
#33
b100 !
b100 .
b1100 "
b1100 -
1%
#34
b11 1
b110 0
b0 2
bx 4
b1001 5
b11 $
b11 )
b110 #
b110 (
0%
#35
b1001 !
b1001 .
bx "
bx -
1%
#36
b110 2
b0 1
b111 0
b110 4
b100 5
b0 $
b0 )
b111 #
b111 (
0%
#37
b100 !
b100 .
b110 "
b110 -
1%
#38
b0 2
b11 4
b100 5
b11 #
b11 (
0%
b11 &
b11 *
#39
b11 "
b11 -
1%
#40
b111 4
b0 5
b111 #
b111 (
0%
#41
b0 !
b0 .
b111 "
b111 -
1%
#42
b100 5
b0 4
b0 #
b0 (
0%
#43
b100 !
b100 .
b0 "
b0 -
1%
#44
b1101 4
b0 5
b1011 #
b1011 (
0%
#45
b0 !
b0 .
b1101 "
b1101 -
1%
#46
b110 5
b1111 4
b1001 #
b1001 (
0%
#47
b110 !
b110 .
b1111 "
b1111 -
1%
