ALU/alu.sv
`define ALU_SUB 2'b00
`define ALU_COMP 2'b01
`define ALU_SUM 2'b10
`define ALU_CONV 2'b11

module sync_arith_unit_4 (i_op, i_arg_A, i_arg_B, i_clk, i_reset, o_result, o_status);

	parameter N = 2;
	parameter M = 4;

	input logic [N-1:0] i_op;
	input logic [M-1:0] i_arg_A;
	input logic [M-1:0] i_arg_B;
	input logic i_clk;
	input logic i_reset;

	output logic [M-1:0] o_result;
	output logic [3:0] o_status;
	
	logic [M-1:0] temp_B;
	logic [M-1:0] comp_A;
	logic [M-1:0] comp_B;
	logic carry;
	logic [M-1:0] sum;
	logic signed sign_A;
	logic signed sign_B;
	logic signed sign_A2;
	logic signed sign_B2;
	
	logic signed [3:0] temp_B_signed;
    logic signed [3:0] result_signed;
    logic [4:0] result_abs;
	
	
	/* Positive edge changes */
	
	always @(posedge i_clk) begin
    	
    		/* Zeroing the status output */
    		
    		o_status = 4'b0000; 
    		
    		/* starting the switch case for all operation options */
    		
    		case (i_op)
    			
    			/*------------FIRST OPERATION------------*/
    			
    			`ALU_SUB:  begin // A-2*B
    					/*
    					sign_A = $signed(i_arg_A);
    					sign_B = $signed(i_arg_B);
    					
    					temp_B = (sign_B << 1);
    					
    					o_result = i_arg_A - temp_B; */
    					
     					temp_B_signed = $signed(i_arg_B) << 1; // Calculate 2*B with signed extension

   						 result_signed = $signed(i_arg_A) - temp_B_signed; // Subtract A - 2*B

    					// Check for overflow in the signed subtraction
    					if (result_signed >= 8 || result_signed < -7) begin
      						 // Overflow occurred, handle accordingly (setting flags, clamping, etc.)
        					 // For example:
       						 result_signed = -8; // Clamping to the minimum negative value
       						 o_status <= 4'b1000; // Set overflow flag
    					end

   						// Convert result back to unsigned for output
   						if (result_signed < 0) begin
        					result_abs = -result_signed; // Get absolute value
        						o_result <= {1'b1, result_abs[3:1]}; // Set sign bit and output the absolute value
   						 end else begin
        					o_result <= i_arg_A - (i_arg_B << 1); // Unsigned subtraction
    					end
    			           end
    					
    					/*
    					if (i_arg_A >= temp_B) begin       										
    						carry = 0;   	   											
    					end 
    					else begin   	    									
    						carry = 1;      											
    					end
    					
    					if (carry == 0) begin
    						
    						o_result = i_arg_A - temp_B;
    						
    					end
 						else begin
 						
 							o_result = 0;
 							
 						end   					
    					*/
    				  
    						
            		
            		
            			
            	/*------------SECOND OPERATION------------*/
            			
            	/* Operation of comparing input A with input B */
            	
            		`ALU_COMP: begin
                    	 
                    	/* if A is smaller than B then the output is NOT 0 */ 
                    	
                		if ((i_arg_A[M-1] == 1) && (i_arg_B[M-1] == 0)) begin
                		
                    			o_result = 2'b01; 
                    			
                		end 
                		
                		/* if A is bigger than B then the output is 0 */ 
                		
                		else if (((i_arg_A[M-1] == 0) && (i_arg_B[M-1] == 1)) || (i_arg_A == i_arg_B)) begin
                		
                    			o_result = 0; // Output 0 if A >= B
                    			
                		end
                		else if ((i_arg_A[M-1] == 0) && (i_arg_B[M-1] == 0)) begin
                		
                			if (i_arg_A < i_arg_B) begin
                			
                				o_result = 2'b01; 
                				
                			end
                			else begin 
                			
                				o_result = 0;
                				
                			end
                			
                		end
                		else if ((i_arg_A[M-1] == 1) && (i_arg_B[M-1] == 1)) begin
                			comp_A = i_arg_A;
                			comp_B = i_arg_B;
                			
                			comp_A[M-1] = 0;
                			comp_B[M-1] = 0;
                			
                			if (comp_A > comp_B) begin
                			
                				o_result = 1;
                			
                			end 
                			else begin
                			
                				o_result = 0;
                			
                			end
                		
                		end

            		end 
            	
            	
            	
            	/*------------THIRD OPERATION------------*/ 
            	
            	/* (A+B)[B] = 0 */
            			
        			
        			`ALU_SUM : begin
        				
        				sign_A2 = $signed(i_arg_A);
        				sign_B2 = $signed(i_arg_B);
        				
        				o_result = sign_A2 + sign_B2;
        				o_result = o_result & ~(1 << i_arg_B);
        				
        				
        			
                    end
                    	
                    	
               	/*------------FOURTH OPERATION------------*/		
               		
                	/* Fourth operation, conversion from Two's compliment into sign magnitude (U2 into ZM)*/
                    			
               		`ALU_CONV: begin
    				
    					/* if the number is negative, we invert all but first bits, then add 1 */
    				
    					if(i_arg_A[M-1] == 1) begin
    				
        					o_result = {1'b1, ~(i_arg_A[M-2:0]) + 1'b1};
        				
    					end 
    				
    					/* if the number is positive, then the output is the number itself*/
    				
    					else begin
    				
        					o_result = i_arg_A;
        				
    					end
    					
					end
    			
                    //default:
                    
			endcase
    	end
endmodule

ALU/testbench.sv
`timescale 1ps/1ps
`include "./alu.sv"


module testbench;

    parameter test_N = 2;
    parameter test_M = 4;

    
    reg [test_N-1:0] test_op;
    reg [test_M-1:0] test_arg_A;
    reg [test_M-1:0] test_arg_B;
    reg test_clk;
    reg test_reset;
    
    wire [test_M-1:0] simulation_test_result;
    wire [3:0] simulation_test_status;

    //wire [test_M-1:0] synthesis_test_result;
    //wire [3:0] synthesis_test_status;
    
    sync_arith_unit_4 #(.N(test_N), .M(test_M))
    alu_model_simulation
    					(.i_arg_A(test_arg_A),
    					 .i_arg_B(test_arg_B),
    					 .i_op(test_op),
    					 .i_clk(test_clk),
    				     .i_reset(test_reset),
    				     .o_result(simulation_test_result), 
    			   	     .o_status(simulation_test_status));
	
	/*
	sync_arith_unit_24_syn
    alu_model_synthesis 	
    					(.i_arg_A(s_arg_A),
     					 .i_arg_B(s_arg_B),
      					 .i_op(s_op),
       					 .i_clk(s_clk),
        				 .i_reset(s_reset),
         				 .o_result(synthesis_s_result),
          				 .o_status(synthesis_s_status));
	*/
	
	initial begin
		
		$dumpfile("signals.vcd");
		$dumpvars(0, testbench);
		
		/*---------FIRST OPERATION TEST---------*/
		
		test_op = 2'b00;
		test_reset = 1'b1;
		
		/* A = 3, B = 1 */
		test_clk = 0;
		test_arg_A = 4'b0011;
		test_arg_B = 4'b0001;
		#1
        test_clk = 1;
        #1
        /* expected output: 0001 */

		/* A = 3, B = -1 */
		test_clk = 0;
		test_arg_A = 4'b0011;
		test_arg_B = 4'b1111;
		#1
        test_clk = 1;
        #1
        /* expected output: 0101 */
        
        /* A = 4, B = 2 */
		test_clk = 0;
		test_arg_A = 4'b0100;
		test_arg_B = 4'b0010;
		#1
        test_clk = 1;
        #1
        /* expected output: 0000 */
        
        /* A = 7, B = 2 */
		test_clk = 0;
		test_arg_A = 4'b0111;
		test_arg_B = 4'b0010;
		#1
        test_clk = 1;
        #1
        /* expected output: 0011 */
        
		/* A = 4, B =  3*/
		test_clk = 0;
		test_arg_A = 4'b0100;
		test_arg_B = 4'b0011;
		#1
        test_clk = 1;
        #1   
        /* expected output: 1101 */
        
        /* A = -4, B = -2 */
		test_clk = 0;
		test_arg_A = 4'b1100;
		test_arg_B = 4'b1110;
		#1
        test_clk = 1;
        #1   
        /* expected output: 0000 */
        
        /* A = 2, B =  3*/
		test_clk = 0;
		test_arg_A = 4'b0010;
		test_arg_B = 4'b0011;
		#1
        test_clk = 1;
        #1   
        /* expected output: 1101 */
        
        /* A = 2, B =  -2*/
		test_clk = 0;
		test_arg_A = 4'b0010;
		test_arg_B = 4'b0010;
		#1
        test_clk = 1;
        #1   
        /* expected output: 1101 */
            		
        /* A = 3, B =  3*/
		test_clk = 0;
		test_arg_A = 4'b0011;
		test_arg_B = 4'b0011;
		#1
        test_clk = 1;
        #1   
        /* expected output: 1101 */
            		
		/*---------SECOND OPERATION TEST---------*/
		
		test_op = 2'b01;
		/*
		/* A = 3, B = 5 */
		test_clk = 0;
		test_arg_A = 4'b0011;
		test_arg_B = 4'b0101;
		#1
        test_clk = 1;
        #1
        /* expected output: 1 */

		/* A = 7, B = 4 */
		test_clk = 0;
		test_arg_A = 4'b0111;
		test_arg_B = 4'b0100;
		#1
        test_clk = 1;
        #1
        /* expected output:  */
        
        
        /* A = -4, B = 3 */
		test_clk = 0;
		test_arg_A = 4'b1100;
		test_arg_B = 4'b0011;
		#1
        test_clk = 1;
        #1
        /* expected output: 1 */
        
        
        /* A = -3, B = -3 */
		test_clk = 0;
		test_arg_A = 4'b1101;
		test_arg_B = 4'b1101;
		#1
        test_clk = 1;
        #1
        /* expected output: 0 */
        
        /* A = 4, B = -5 */
		test_clk = 0;
		test_arg_A = 4'b0100;
		test_arg_B = 4'b1011;
		#1
        test_clk = 1;
        #1 
		/* expected output: 0 */
		

		/*---------THIRD OPERATION TEST---------*/
		
		test_op = 2'b10;
		
        /* A = 2, B = 3 */
		test_clk = 0;
		test_arg_A = 4'b0010;
		test_arg_B = 4'b0011;
		#1
        test_clk = 1;
        #1 
		/* expected output: 0101 -> 0001 */		
		
		/*---------FOURTH OPERATION TEST---------*/
		/*  */
		
		test_op = 2'b11;
		
		/* A = -5*/
		test_clk = 0;
        test_arg_A = 4'b1011;
        #1
        test_clk = 1;
        #1
        

		/* A = 0 */
		test_clk = 0;
        test_arg_A = 4'b0000;
        #1
        test_clk = 1;
        #1

		/* A = -7 */
		test_clk = 0;
        test_arg_A = 4'b1001;
        #1
        test_clk = 1;
        #1

		/* A = 3 */
        test_clk = 0;
        test_arg_A = 4'b0011;
        #1
        test_clk = 1;
        #1


		
		$finish;
		
	end
	
endmodule

ALU/signals.vcd
$date
	Tue Dec  5 17:56:12 2023
$end
$version
	Icarus Verilog
$end
$timescale
	1ps
$end
$scope module testbench $end
$var wire 4 ! simulation_test_status [3:0] $end
$var wire 4 " simulation_test_result [3:0] $end
$var reg 4 # test_arg_A [3:0] $end
$var reg 4 $ test_arg_B [3:0] $end
$var reg 1 % test_clk $end
$var reg 2 & test_op [1:0] $end
$var reg 1 ' test_reset $end
$scope module alu_model_simulation $end
$var wire 4 ( i_arg_A [3:0] $end
$var wire 4 ) i_arg_B [3:0] $end
$var wire 1 % i_clk $end
$var wire 2 * i_op [1:0] $end
$var wire 1 ' i_reset $end
$var reg 4 + comp_A [3:0] $end
$var reg 4 , comp_B [3:0] $end
$var reg 4 - o_result [3:0] $end
$var reg 4 . o_status [3:0] $end
$var reg 5 / result_abs [4:0] $end
$var reg 4 0 result_signed [3:0] $end
$var reg 1 1 sign_A2 $end
$var reg 1 2 sign_B2 $end
$var reg 4 3 temp_B_signed [3:0] $end
$upscope $end
$upscope $end
$enddefinitions $end
#0
$dumpvars
bx 3
x2
x1
bx 0
bx /
bx .
bx -
bx ,
bx +
b0 *
b1 )
b11 (
1'
b0 &
0%
b1 $
b11 #
bx "
bx !
$end
#1
b1 "
b1 -
b1 0
b10 3
b0 !
b0 .
1%
#2
b1111 $
b1111 )
0%
#3
b101 "
b101 -
b101 0
b1110 3
1%
#4
b10 $
b10 )
b100 #
b100 (
0%
#5
b0 "
b0 -
b0 0
b100 3
1%
#6
b111 #
b111 (
0%
#7
b11 "
b11 -
b11 0
1%
#8
b11 $
b11 )
b100 #
b100 (
0%
#9
b1001 "
b1001 -
b10 /
b1110 0
b110 3
1%
#10
b1110 $
b1110 )
b1100 #
b1100 (
0%
#11
b0 "
b0 -
b0 0
b1100 3
1%
#12
b11 $
b11 )
b10 #
b10 (
0%
#13
b1010 "
b1010 -
b100 /
b1100 0
b110 3
1%
#14
b10 $
b10 )
0%
#15
b1001 "
b1001 -
b10 /
b1110 0
b100 3
1%
#16
b11 $
b11 )
b11 #
b11 (
0%
#17
b11 /
b1101 0
b110 3
1%
#18
b101 $
b101 )
0%
b1 &
b1 *
#19
b1 "
b1 -
1%
#20
b100 $
b100 )
b111 #
b111 (
0%
#21
b0 "
b0 -
1%
#22
b11 $
b11 )
b1100 #
b1100 (
0%
#23
b1 "
b1 -
1%
#24
b1101 $
b1101 )
b1101 #
b1101 (
0%
#25
b0 "
b0 -
1%
#26
b1011 $
b1011 )
b100 #
b100 (
0%
#27
1%
#28
b11 $
b11 )
b10 #
b10 (
0%
b10 &
b10 *
#29
b111 "
b111 -
12
01
1%
#30
b1011 #
b1011 (
0%
b11 &
b11 *
#31
b1101 "
b1101 -
1%
#32
b0 #
b0 (
0%
#33
b0 "
b0 -
1%
#34
b1001 #
b1001 (
0%
#35
b1111 "
b1111 -
1%
#36
b11 #
b11 (
0%
#37
b11 "
b11 -
1%
