ALU/alu.sv
`define ALU_SUB 2'b00
`define ALU_COMP 2'b01
`define ALU_SUM 2'b10
`define ALU_CONV 2'b11

module sync_arith_unit_4 (i_op, i_arg_A, i_arg_B, i_clk, i_reset, o_result, o_status);

	parameter N = 2;
	parameter M = 4;

	input logic [N-1:0] i_op;
	input logic [M-1:0] i_arg_A;
	input logic [M-1:0] i_arg_B;
	input logic i_clk;
	input logic i_reset;

	output logic [M-1:0] o_result;
	output logic [3:0] o_status;
	
	logic [M-1:0] temp_B;
	logic [M-1:0] comp_A;
	logic [M-1:0] comp_B;
	logic carry;
	logic [M-1:0] sum;
	logic signed sign_A;
	logic signed sign_B;
	
	/* Positive edge changes */
	
	always @(posedge i_clk) begin
    	
    		/* Zeroing the status output */
    		
    		o_status = 4'b0000; 
    		
    		/* starting the switch case for all operation options */
    		
    		case (i_op)
    			
    			/*------------FIRST OPERATION------------*/
    			
    			`ALU_SUB:  begin // A-2*B
    					
    					sign_A = $signed(i_arg_A);
    					sign_B = $signed(i_arg_B);
    					
    					temp_B = (i_arg_B << 1);
    					
    					o_result = i_arg_A - temp_B;
    					/*
    					if (i_arg_A >= temp_B) begin       										
    						carry = 0;   	   											
    					end 
    					else begin   	    									
    						carry = 1;      											
    					end
    					
    					if (carry == 0) begin
    						
    						o_result = i_arg_A - temp_B;
    						
    					end
 						else begin
 						
 							o_result = 0;
 							
 						end   					
    					*/
    				   end
    						
            		
            		
            			
            	/*------------SECOND OPERATION------------*/
            			
            	/* Operation of comparing input A with input B */
            	
            		`ALU_COMP: begin
                    	 
                    	/* if A is smaller than B then the output is NOT 0 */ 
                    	
                		if ((i_arg_A[M-1] == 1) && (i_arg_B[M-1] == 0)) begin
                		
                    			o_result = 2'b01; 
                    			
                		end 
                		
                		/* if A is bigger than B then the output is 0 */ 
                		
                		else if (((i_arg_A[M-1] == 0) && (i_arg_B[M-1] == 1)) || (i_arg_A == i_arg_B)) begin
                		
                    			o_result = 0; // Output 0 if A >= B
                    			
                		end
                		else if ((i_arg_A[M-1] == 0) && (i_arg_B[M-1] == 0)) begin
                		
                			if (i_arg_A < i_arg_B) begin
                			
                				o_result = 2'b01; 
                				
                			end
                			else begin 
                			
                				o_result = 0;
                				
                			end
                			
                		end
                		else if ((i_arg_A[M-1] == 1) && (i_arg_B[M-1] == 1)) begin
                			comp_A = i_arg_A;
                			comp_B = i_arg_B;
                			
                			comp_A[M-1] = 0;
                			comp_B[M-1] = 0;
                			
                			if (comp_A > comp_B) begin
                			
                				o_result = 1;
                			
                			end 
                			else begin
                			
                				o_result = 0;
                			
                			end
                		
                		end

            		end 
            	
            	
            	
            	/*------------THIRD OPERATION------------*/ 
            	
            	/* (A+B)[B] = 0 */
            			
        			
        			//`ALU_SUM begin
        			
        			
                    //end
                    	
                    	
               	/*------------FOURTH OPERATION------------*/		
               		
                	/* Fourth operation, conversion from Two's compliment into sign magnitude (U2 into ZM)*/
                    			
               		`ALU_CONV: begin
    				
    					/* if the number is negative, we invert all but first bits, then add 1 */
    				
    					if(i_arg_A[M-1] == 1) begin
    				
        					o_result = {1'b1, ~(i_arg_A[M-2:0]) + 1'b1};
        				
    					end 
    				
    					/* if the number is positive, then the output is the number itself*/
    				
    					else begin
    				
        					o_result = i_arg_A;
        				
    					end
    					
					end
    			
                    //default:
                    
			endcase
    	end
endmodule

ALU/testbench.sv
`timescale 1ps/1ps
`include "./alu.sv"


module testbench;

    parameter test_N = 2;
    parameter test_M = 4;

    
    reg [test_N-1:0] test_op;
    reg [test_M-1:0] test_arg_A;
    reg [test_M-1:0] test_arg_B;
    reg test_clk;
    reg test_reset;
    
    wire [test_M-1:0] simulation_test_result;
    wire [3:0] simulation_test_status;

    //wire [test_M-1:0] synthesis_test_result;
    //wire [3:0] synthesis_test_status;
    
    sync_arith_unit_4 #(.N(test_N), .M(test_M))
    alu_model_simulation
    					(.i_arg_A(test_arg_A),
    					 .i_arg_B(test_arg_B),
    					 .i_op(test_op),
    					 .i_clk(test_clk),
    				     .i_reset(test_reset),
    				     .o_result(simulation_test_result), 
    			   	     .o_status(simulation_test_status));
	
	/*
	sync_arith_unit_24_syn
    alu_model_synthesis 	
    					(.i_arg_A(s_arg_A),
     					 .i_arg_B(s_arg_B),
      					 .i_op(s_op),
       					 .i_clk(s_clk),
        				 .i_reset(s_reset),
         				 .o_result(synthesis_s_result),
          				 .o_status(synthesis_s_status));
	*/
	
	initial begin
		
		$dumpfile("signals.vcd");
		$dumpvars(0, testbench);
		
		/*---------FIRST OPERATION TEST---------*/
		
		test_op = 2'b00;
		test_reset = 1'b1;
		
		/* A = 3, B = 1 */
		test_clk = 0;
		test_arg_A = 4'b0011;
		test_arg_B = 4'b0001;
		#1
        test_clk = 1;
        #1
        /* expected output: 0001 */

		/* A = 3, B = -1 */
		test_clk = 0;
		test_arg_A = 4'b0011;
		test_arg_B = 4'b1111;
		#1
        test_clk = 1;
        #1
        /* expected output: 0101 */
        
        /* A = 4, B = 2 */
		test_clk = 0;
		test_arg_A = 4'b0100;
		test_arg_B = 4'b0010;
		#1
        test_clk = 1;
        #1
        /* expected output: 0000 */
        
        /* A = 7, B = 2 */
		test_clk = 0;
		test_arg_A = 4'b0111;
		test_arg_B = 4'b0010;
		#1
        test_clk = 1;
        #1
        /* expected output: 0011 */
        
		/* A = 4, B = 5 */
		test_clk = 0;
		test_arg_A = 4'b0100;
		test_arg_B = 4'b0110;
		#1
        test_clk = 1;
        #1   
        /* expected output: 0 */
            		
		/*---------SECOND OPERATION TEST---------*/
		
		test_op = 2'b01;
		/*
		/* A = 3, B = 5 */
		test_clk = 0;
		test_arg_A = 4'b0011;
		test_arg_B = 4'b0101;
		#1
        test_clk = 1;
        #1
        /* expected output: 1 */

		/* A = 7, B = 4 */
		test_clk = 0;
		test_arg_A = 4'b0111;
		test_arg_B = 4'b0100;
		#1
        test_clk = 1;
        #1
        /* expected output:  */
        
        
        /* A = -4, B = 3 */
		test_clk = 0;
		test_arg_A = 4'b1100;
		test_arg_B = 4'b0011;
		#1
        test_clk = 1;
        #1
        /* expected output: 1 */
        
        
        /* A = -3, B = -3 */
		test_clk = 0;
		test_arg_A = 4'b1101;
		test_arg_B = 4'b1101;
		#1
        test_clk = 1;
        #1
        /* expected output: 0 */
        
        /* A = 4, B = -5 */
		test_clk = 0;
		test_arg_A = 4'b0100;
		test_arg_B = 4'b1011;
		#1
        test_clk = 1;
        #1 
		/* expected output: 0 */
		

		/*---------THIRD OPERATION TEST---------*/
		
		test_op = 2'b10;
		
		/*---------FOURTH OPERATION TEST---------*/
		/*  */
		
		test_op = 2'b11;
		
		/* A = -5*/
		test_clk = 0;
        test_arg_A = 4'b1011;
        #1
        test_clk = 1;
        #1
        

		/* A = 0 */
		test_clk = 0;
        test_arg_A = 4'b0000;
        #1
        test_clk = 1;
        #1

		/* A = -7 */
		test_clk = 0;
        test_arg_A = 4'b1001;
        #1
        test_clk = 1;
        #1

		/* A = 3 */
        test_clk = 0;
        test_arg_A = 4'b0011;
        #1
        test_clk = 1;
        #1


		
		$finish;
		
	end
	
endmodule

ALU/signals.vcd
$date
	Mon Dec  4 17:09:22 2023
$end
$version
	Icarus Verilog
$end
$timescale
	1ps
$end
$scope module testbench $end
$var wire 4 ! simulation_test_status [3:0] $end
$var wire 4 " simulation_test_result [3:0] $end
$var reg 4 # test_arg_A [3:0] $end
$var reg 4 $ test_arg_B [3:0] $end
$var reg 1 % test_clk $end
$var reg 2 & test_op [1:0] $end
$var reg 1 ' test_reset $end
$scope module alu_model_simulation $end
$var wire 4 ( i_arg_A [3:0] $end
$var wire 4 ) i_arg_B [3:0] $end
$var wire 1 % i_clk $end
$var wire 2 * i_op [1:0] $end
$var wire 1 ' i_reset $end
$var reg 4 + comp_A [3:0] $end
$var reg 4 , comp_B [3:0] $end
$var reg 4 - o_result [3:0] $end
$var reg 4 . o_status [3:0] $end
$var reg 1 / sign_A $end
$var reg 1 0 sign_B $end
$var reg 4 1 temp_B [3:0] $end
$upscope $end
$upscope $end
$enddefinitions $end
#0
$dumpvars
bx 1
x0
x/
bx .
bx -
bx ,
bx +
b0 *
b1 )
b11 (
1'
b0 &
0%
b1 $
b11 #
bx "
bx !
$end
#1
b1 "
b1 -
b10 1
10
1/
b0 !
b0 .
1%
#2
b1111 $
b1111 )
0%
#3
b101 "
b101 -
b1110 1
1%
#4
b10 $
b10 )
b100 #
b100 (
0%
#5
b0 "
b0 -
b100 1
00
0/
1%
#6
b111 #
b111 (
0%
#7
b11 "
b11 -
1/
1%
#8
b110 $
b110 )
b100 #
b100 (
0%
#9
b1000 "
b1000 -
b1100 1
0/
1%
#10
b101 $
b101 )
b11 #
b11 (
0%
b1 &
b1 *
#11
b1 "
b1 -
1%
#12
b100 $
b100 )
b111 #
b111 (
0%
#13
b0 "
b0 -
1%
#14
b11 $
b11 )
b1100 #
b1100 (
0%
#15
b1 "
b1 -
1%
#16
b1101 $
b1101 )
b1101 #
b1101 (
0%
#17
b0 "
b0 -
1%
#18
b1011 $
b1011 )
b100 #
b100 (
0%
#19
1%
#20
b1011 #
b1011 (
0%
b11 &
b11 *
#21
b1101 "
b1101 -
1%
#22
b0 #
b0 (
0%
#23
b0 "
b0 -
1%
#24
b1001 #
b1001 (
0%
#25
b1111 "
b1111 -
1%
#26
b11 #
b11 (
0%
#27
b11 "
b11 -
1%
